fantasylcs/__init__.py
fantasylcs/league.py
fantasylcs/player.py
fantasylcs/season.py
fantasylcs/team.py
fantasylcs-1.2.2.dist-info/LICENSE
fantasylcs-1.2.2.dist-info/METADATA
fantasylcs-1.2.2.dist-info/WHEEL
fantasylcs-1.2.2.dist-info/top_level.txt
fantasylcs-1.2.2.dist-info/RECORD
