Metadata-Version: 2.1
Name: fantasylcs
Version: 1.2.2
Summary: An unofficial FantasyLCS API Wrapper.
Home-page: https://github.com/kodycode/Fantasy-LCS-API-Wrapper
Author: Kody Thach
License: MIT License
Platform: UNKNOWN
Requires-Dist: requests (==2.20.0)
